ida_cli/__init__.py
ida_cli/cli.py
ida_cli/daemon.py
ida_cli/env_setup.py
ida_cli/helpers.py
ida_cli/idb.py
ida_cli/protocol.py
ida_cli/py.typed
ida_cli/schemas.py
ida_cli/commands/__init__.py
ida_cli/commands/analysis.py
ida_cli/commands/functions.py
ida_cli/commands/meta.py
ida_cli/commands/mutate.py
ida_cli/commands/search.py
ida_cli/commands/xrefs.py
ida_cli-0.1.1.dist-info/METADATA
ida_cli-0.1.1.dist-info/WHEEL
ida_cli-0.1.1.dist-info/entry_points.txt
ida_cli-0.1.1.dist-info/RECORD
