Metadata-Version: 2.4
Name: ida-cli
Version: 0.1.1
Summary: CLI tool for reverse engineering with IDA's idalib
Author-email: Darvell <contact@darvell.me>
License-Expression: MIT
Keywords: cli,ida,idalib,reverse-engineering
Classifier: Development Status :: 3 - Alpha
Classifier: Environment :: Console
Classifier: Intended Audience :: Developers
Classifier: License :: OSI Approved :: MIT License
Classifier: Programming Language :: Python :: 3
Classifier: Programming Language :: Python :: 3.10
Classifier: Programming Language :: Python :: 3.11
Classifier: Programming Language :: Python :: 3.12
Classifier: Topic :: Security
Classifier: Topic :: Software Development :: Disassemblers
Requires-Python: >=3.10
Requires-Dist: click>=8.0
Requires-Dist: pydantic>=2.0
Provides-Extra: dev
Requires-Dist: mypy>=1.0; extra == 'dev'
Requires-Dist: pytest-cov>=4.0; extra == 'dev'
Requires-Dist: pytest>=7.0; extra == 'dev'
Requires-Dist: ruff>=0.1.0; extra == 'dev'
